{"template":"../src/pages/blog.js","sharedHashesByProp":{},"data":{"posts":[{"id":6,"title":"rohan","content":"## rohan\n\n\n**this is strong**","created_at":"2019-08-30T09:03:44.948Z","updated_at":"2019-08-30T09:03:44.962Z","image":[]},{"id":5,"title":"It's already five O'clock","content":"#### I'm writing h4 now\n\nand then maybe now.\n\n\n__underlined text is also working ??__","created_at":"2019-08-30T08:59:33.329Z","updated_at":"2019-08-30T09:02:20.205Z","image":[]},{"id":4,"title":"Test!","content":"## This is H2!\n\n\nTwo returns\n\n\n**strong !!**\n\n\n```code blocksss```","created_at":"2019-08-30T08:42:18.006Z","updated_at":"2019-08-30T08:42:18.033Z","image":[]},{"id":2,"title":"テストその２","content":"これは、テストだよ。\n**さらに、太文字**\n\n\n改行２行してますー！\n","created_at":"2019-08-30T06:40:46.790Z","updated_at":"2019-08-30T08:39:51.760Z","image":[]},{"id":3,"title":"This is a test for texts","content":"# this is H1 because this is markdown.\n\nand I put return abobe\n\n\n**this should be strong text.**","created_at":"2019-08-30T06:47:10.137Z","updated_at":"2019-08-30T06:47:10.154Z","image":[]},{"id":1,"title":"電車〜","content":"頑張れ電車＝＝＝＝","created_at":"2019-08-29T13:56:27.003Z","updated_at":"2019-08-29T13:56:27.028Z","image":[]}]},"path":"blog"}
